[{"Id":"0.5379883564186974","firstName":"anil","LastName":"kumar","useremail":"anil","userPhoneNumber":"9513574565","gender":"Male","dfb":"1997-07-01","ip_address":"564564","Accepted":"Yes"},{"Id":"0.9250768832620448","firstName":"anil","LastName":"kumar","useremail":"anil","userPhoneNumber":"9513574565","gender":"Male","dfb":"1997-07-01","ip_address":"564564","Accepted":"Yes"},{"Id":"0.6106070079790769","firstName":"uttam sir","LastName":"kumar","useremail":"uttam sir","userPhoneNumber":"9513574565","gender":"Male","dfb":"1997-07-01","ip_address":"564564","Accepted":"Yes"},{"Id":"0.8058328536882853","firstName":"anilweddf","LastName":"kumar","useremail":"anilweddf","userPhoneNumber":"9513574565","gender":"Male","dfb":"1997-07-01","ip_address":"564564","Accepted":"Yes"},{"Id":"0.8202389030835826","firstName":"anil","LastName":"kumar","useremail":"anil","userPhoneNumber":"9513574565","gender":"Male","dfb":"1997-07-01","ip_address":"564564","Accepted":"Yes"},{"Id":"0.7928641935084835","firstName":"anilwfqegwrtg","LastName":"kumar","useremail":"anilwfqegwrtg","userPhoneNumber":"9513574565","gender":"Male","dfb":"1997-07-01","ip_address":"564564","Accepted":"Yes"},{"Id":"0.4882790603728864","firstName":"naveen","LastName":"kumar","useremail":"naveen","userPhoneNumber":"9513574565","gender":"Male","dfb":"1997-07-01","ip_address":"564564","Accepted":"Yes"},{"Id":"0.28042644741324807","firstName":"manu","LastName":"kumar","useremail":"manu","userPhoneNumber":"9513574565","gender":"Male","dfb":"1997-07-01","ip_address":"564564","Accepted":"Yes"},{"Id":"0.6615183266323716","firstName":"anil","LastName":"kumar","useremail":"anil","userPhoneNumber":"9513574565","gender":"Male","dfb":"1997-07-01","ip_address":"564564","Accepted":"Yes"},{"Id":"0.8344581083527711","firstName":"anil","LastName":"kumar","useremail":"anil","userPhoneNumber":"9513574565","gender":"Male","dfb":"1997-07-01","ip_address":"564564","Accepted":"Yes"},{"Id":"0.2961037526175183","firstName":"anil1qd","LastName":"qewr","useremail":"anil1qd","userPhoneNumber":"9513574565","gender":"Male","dfb":"1997-07-01","ip_address":"564564","Accepted":"Yes"},{"Id":"0.0640157673169266","firstName":"anil","LastName":"wfqerws","useremail":"anil","userPhoneNumber":"9513574565","gender":"Male","dfb":"1997-07-01","ip_address":"564564","Accepted":"Yes"},{"Id":"0.5015897787262136","firstName":"anil","LastName":"kumar","useremail":"anil","userPhoneNumber":"9513574565","gender":"Male","dfb":"1997-07-01","ip_address":"564564","Accepted":"Yes"},{"Id":"0.2467501726052288","firstName":"anil","LastName":"kumar","useremail":"anil","userPhoneNumber":"9513574565","gender":"Male","dfb":"1997-07-01","ip_address":"564564","Accepted":"Yes"},{"Id":"0.2581912833065363","firstName":"anil","LastName":"kumar","useremail":"anil","userPhoneNumber":"9513574565","gender":"Male","dfb":"1997-07-01","ip_address":"564564","Accepted":"Yes"},{"Id":"0.6409232059459964","firstName":"anil","LastName":"kumar","useremail":"anil","userPhoneNumber":"9513574565","gender":"Male","dfb":"1997-07-01","ip_address":"564564","Accepted":"Yes"},{"Id":"0.5979153223442559","firstName":"anil","LastName":"kumar","useremail":"anil","userPhoneNumber":"9513574565","gender":"Male","dfb":"1997-07-01","ip_address":"564564","Accepted":"Yes"},{"Id":"0.50681146295192","firstName":"anil","LastName":"kumar","useremail":"anil","userPhoneNumber":"9513574565","gender":"Male","dfb":"1997-07-01","ip_address":"564564","Accepted":"Yes"},{"Id":"0.22640600327388083","firstName":"anil","LastName":"kumar","useremail":"anil","userPhoneNumber":"9513574565","gender":"Male","dfb":"1997-07-01","ip_address":"564564","Accepted":"Yes"},{"Id":"0.4930213435956776","firstName":"anil","LastName":"kumar","useremail":"anil","userPhoneNumber":"9513574565","gender":"Male","dfb":"1997-07-01","ip_address":"564564","Accepted":"Yes"},{"Id":"0.09969505135069934","firstName":"anil","LastName":"kumar","useremail":"anil","userPhoneNumber":"9513574565","gender":"Male","dfb":"1997-07-01","ip_address":"564564","Accepted":"Yes"},{"Id":"0.36019226860222076","firstName":"anil","LastName":"kumar","useremail":"anil","userPhoneNumber":"9513574565","gender":"Male","dfb":"1997-07-01","ip_address":"564564","Accepted":"Yes"},{"Id":"0.20197751072967507","firstName":"anil","LastName":"kumar","useremail":"anil","userPhoneNumber":"9513574565","gender":"Male","dfb":"1997-07-01","ip_address":"564564","Accepted":"Yes"},{"Id":"0.6069244948939827","firstName":"anilt","LastName":"kumar","useremail":"anilt","userPhoneNumber":"9513574565","gender":"Male","dfb":"1997-07-01","ip_address":"564564","Accepted":"Yes"},{"Id":"0.18656334929314466","firstName":"anil","LastName":"kumar","useremail":"anil","userPhoneNumber":"9513574565","gender":"Male","dfb":"1997-07-01","ip_address":"564564","Accepted":"Yes"}]