[{"Id":"0.12502543421424228","firstName":"anil","LastName":"kumar","useremail":"anil123@gmail.com","userPhoneNumber":"9513574565","gender":"Male","dfb":"1997-07-01","ip_address":"564564","Accepted":"Yes","imagPath":""},{"Id":"0.6384946299843908","firstName":"anilwfqegwrtg","LastName":"kumar","useremail":"anil123@gmail.com","userPhoneNumber":"9513574565","gender":"Male","dfb":"1997-07-01","ip_address":"564564","Accepted":"Yes","imagPath":""},{"Id":"0.12387829367607273","firstName":"anilweddf","LastName":"kumar","useremail":"anil123@gmail.com","userPhoneNumber":"9513574565","gender":"Male","dfb":"1997-07-01","ip_address":"564564","Accepted":"Yes","imagPath":""},null,null,null,null,null,null,null,null,{"Id":"0.12502543421424228","firstName":"anil","LastName":"kumar","useremail":"anil123@gmail.com","userPhoneNumber":"9513574565","gender":"Male","dfb":"1997-07-01","ip_address":"564564","Accepted":"Yes","imagPath":""},{"Id":"0.12502543421424228","firstName":"anil","LastName":"kumar","useremail":"anil123@gmail.com","userPhoneNumber":"9513574565","gender":"Male","dfb":"1997-07-01","ip_address":"564564","Accepted":"Yes","imagPath":""},{"Id":"0.12502543421424228","firstName":"anil","LastName":"kumar","useremail":"anil123@gmail.com","userPhoneNumber":"9513574565","gender":"Male","dfb":"1997-07-01","ip_address":"564564","Accepted":"Yes","imagPath":""},{"Id":"0.12502543421424228","firstName":"anil","LastName":"kumar","useremail":"anil123@gmail.com","userPhoneNumber":"9513574565","gender":"Male","dfb":"1997-07-01","ip_address":"564564","Accepted":"Yes","imagPath":""},{"Id":"0.12502543421424228","firstName":"anil","LastName":"kumar","useremail":"anil123@gmail.com","userPhoneNumber":"9513574565","gender":"Male","dfb":"1997-07-01","ip_address":"564564","Accepted":"Yes","imagPath":""},{"Id":"0.12502543421424228","firstName":"anil","LastName":"kumar","useremail":"anil123@gmail.com","userPhoneNumber":"9513574565","gender":"Male","dfb":"1997-07-01","ip_address":"564564","Accepted":"Yes","imagPath":""},{"Id":"0.12502543421424228","firstName":"anil","LastName":"kumar","useremail":"anil123@gmail.com","userPhoneNumber":"9513574565","gender":"Male","dfb":"1997-07-01","ip_address":"564564","Accepted":"Yes","imagPath":""},{"Id":"0.12502543421424228","firstName":"anil","LastName":"kumar","useremail":"anil123@gmail.com","userPhoneNumber":"9513574565","gender":"Male","dfb":"1997-07-01","ip_address":"564564","Accepted":"Yes","imagPath":""},{"Id":"0.12502543421424228","firstName":"anil","LastName":"kumar","useremail":"anil123@gmail.com","userPhoneNumber":"9513574565","gender":"Male","dfb":"1997-07-01","ip_address":"564564","Accepted":"Yes","imagPath":""},{"Id":"0.12502543421424228","firstName":"anil","LastName":"kumar","useremail":"anil123@gmail.com","userPhoneNumber":"9513574565","gender":"Male","dfb":"1997-07-01","ip_address":"564564","Accepted":"Yes","imagPath":""},null,null,null,null,null,null,null,null,null,null,null,null,null,null,null,null,null,null,null,null,null,null,null,null,null,null,null,null,null,null,null,null,null]